---
layout:     post
title:      "JVM - 对象实例化的几种方式"
subtitle:   " \"JVM Daily Notes - 16\""
date:       2021.01.18 12:29:00
author:     "Wuy"
header-img: "img/post-bg-2020.jpg"
catalog: true
tags:
    - 学习笔记
    - 读书
    - JVM
---

> *"Keep Learning JVM"*

# 对象的实例化

1. 创建对象的方式：
   - `new`/静态方法/工厂静态方法;
   - `Class`的`newInstance()`:
     - 反射的方式，只能调用空参的构造器，权限必须是`public`.
   - `Constructor`的`newInstance()`:
     - 反射的方式，可以调用空参、带参的构造器，权限没有要求。
   - 使用`clone()`
     - 不调用任何构造器，当前类需要实现`Cloneable`接口，实现`clone()`方法。
   - 使用反序列化：
     - 从文件、网络中获取一个对象的二进制字节流；
   - 使用第三方库`Objenesis`。
   
2. 字节码角度看对象创建的过程：

   ```java
   public class CodeTest {
   
       public static void main(String[] args) {
           Object object = new Object();
           System.out.println(object);
       }
   }
   ```

   上述代码反编译后如下：

   ```java
   D:\Program Files\DailyTest\out\production\DailyTest>javap -v -p CodeTest.class
   Classfile /D:/Program Files/DailyTest/out/production/DailyTest/CodeTest.class
     Last modified 2021119; size 561 bytes
     MD5 checksum 0435f671985f2a17d4acf53e15bf3b24
     Compiled from "CodeTest.java"
   public class CodeTest
     minor version: 0
     major version: 52
     flags: (0x0021) ACC_PUBLIC, ACC_SUPER
     this_class: #5                          // CodeTest
     super_class: #2                         // java/lang/Object
     interfaces: 0, fields: 0, methods: 2, attributes: 1
   Constant pool:
      #1 = Methodref          #2.#21         // java/lang/Object."<init>":()V
      #2 = Class              #22            // java/lang/Object
      #3 = Fieldref           #23.#24        // java/lang/System.out:Ljava/io/PrintStream;
      #4 = Methodref          #25.#26        // java/io/PrintStream.println:(Ljava/lang/Object;)V
      #5 = Class              #27            // CodeTest
      #6 = Utf8               <init>
      #7 = Utf8               ()V
      #8 = Utf8               Code
      #9 = Utf8               LineNumberTable
     #10 = Utf8               LocalVariableTable
     #11 = Utf8               this
     #12 = Utf8               LCodeTest;
     #13 = Utf8               main
     #14 = Utf8               ([Ljava/lang/String;)V
     #15 = Utf8               args
     #16 = Utf8               [Ljava/lang/String;
     #17 = Utf8               object
     #18 = Utf8               Ljava/lang/Object;
     #19 = Utf8               SourceFile
     #20 = Utf8               CodeTest.java
     #21 = NameAndType        #6:#7          // "<init>":()V
     #22 = Utf8               java/lang/Object
     #23 = Class              #28            // java/lang/System
     #24 = NameAndType        #29:#30        // out:Ljava/io/PrintStream;
     #25 = Class              #31            // java/io/PrintStream
     #26 = NameAndType        #32:#33        // println:(Ljava/lang/Object;)V
     #27 = Utf8               CodeTest
     #28 = Utf8               java/lang/System
     #29 = Utf8               out
     #30 = Utf8               Ljava/io/PrintStream;
     #31 = Utf8               java/io/PrintStream
     #32 = Utf8               println
     #33 = Utf8               (Ljava/lang/Object;)V
   {
     public CodeTest();
       descriptor: ()V
       flags: (0x0001) ACC_PUBLIC
       Code:
         stack=1, locals=1, args_size=1
            0: aload_0
            1: invokespecial #1                  // Method java/lang/Object."<init>":()V
            4: return
         LineNumberTable:
           line 1: 0
         LocalVariableTable:
           Start  Length  Slot  Name   Signature
               0       5     0  this   LCodeTest;
   
     public static void main(java.lang.String[]);
       descriptor: ([Ljava/lang/String;)V
       flags: (0x0009) ACC_PUBLIC, ACC_STATIC
       Code:
         stack=2, locals=2, args_size=1
            0: new           #2                  // class java/lang/Object
            3: dup
            4: invokespecial #1                  // Method java/lang/Object."<init>":()V
            7: astore_1
            8: getstatic     #3                  // Field java/lang/System.out:Ljava/io/PrintStream;
           11: aload_1
           12: invokevirtual #4                  // Method java/io/PrintStream.println:(Ljava/lang/Object;)V
           15: return
         LineNumberTable:
           line 4: 0
           line 5: 8
           line 6: 15
         LocalVariableTable:
           Start  Length  Slot  Name   Signature
               0      16     0  args   [Ljava/lang/String;
               8       8     1 object   Ljava/lang/Object;
   }
   SourceFile: "CodeTest.java"
   
   ```

   -  其中`new`指令在java堆上为`Object`对象分配内存空间，并将地址压入操作数栈顶；

   - 然后`dup`指令为复制操作数栈顶值，并将其压入栈顶，也就是说此时操作数栈上有连续相同的两个对象地址；

   - `invokespecial`指令调用实例初始化方法`<init>:()V`，注意这个方法是一个实例方法，所以需要从操作数栈顶弹出一个`this`引用，也就是说这一步会弹出一个之前入栈的对象地址；

   - 最后由`return`指令结束方法。

   从上面的五个步骤中可以看出，需要从栈顶弹出一个实例对象的引用，这就是为什么会在`new`指令下面有一个`dup`指令，其实对于每一个`new`指令来说一般编译器都会在其下面生成一个`dup`指令，这是因为实例的初始化方法肯定需要用到一次，然后第二个留给程序员使用，例如给变量赋值，抛出异常等，如果我们不用，那编译器也会生成`dup`指令，在初始化方法调用完成后再从栈顶`pop`出来。

3. 创建对象的六个步骤：

   - 判断对象对应的类是否经过加载、链接、初始化；
   - 为对象分配内存：
     - 如果内存规整：
       - 指针碰撞，一般带有内存整理过程（标记-压缩算法）的垃圾收集器时，使用这种方法；
     - 如果内存不规整：
       - 虚拟机需要维护一个列表；
       - 空闲列表分配；
     - 选择哪种分配方式由Java堆是否规整决定，而Java堆是否规整又由所采用的垃圾收集器是否带有压缩整理功能决定；
   - 处理并发安全问题：
     - 采用CAS失败重试、区域加锁保证更新的原子性；
     - 每个线程预先分配一块TLAB；
       - 通过`-XX:+/-UseTLAB`来决定；
   - 初始化分配到的空间（零值初始化）：
     - 所有属性设置默认值，保证对象实例字段在不赋值的时候可以直接使用；
   - 设置对象的对象头：
     - 将对象的所属类（即类的元数据信息）、对象的`HashCode`和对象的GC信息、锁信息等数据存放在对象的对象头中。这个过程的具体设置方式取决于JVM的实现。
   - 执行`init`方法进行初始化：
     - 属性的显示初始化；
     - 代码块中初始化；
     - 构造器中初始化。

   